xyz_parser/__init__.py
xyz_parser/parser.py
xyz_parser-0.0.15.dist-info/METADATA
xyz_parser-0.0.15.dist-info/WHEEL
xyz_parser-0.0.15.dist-info/RECORD
