Metadata-Version: 2.4
Name: xyz_parser
Version: 0.0.15
Summary: Parser of the xyz file format. Used in chemistry.
Project-URL: repository, https://github.com/the-pawel-wojcik/xyz.git
Author-email: Paweł Wójcik <the.pawel.wojcik@gmail.com>
Keywords: chemistry,parsers
Requires-Python: >=3.13
